{"status": "📊 **وضعیت تفصیلی سرور:**\n➖➖➖➖➖➖➖➖➖➖➖➖\n🤖 **وضعیت ربات:**\n▫️ وضعیت: `فعال ✅`\n\n💻 **اطلاعات سیستم:**\n▫️ سیستم عامل: `Linux-6.2.16-x86_64-with-glibc2.40`\n▫️ معماری: `x86_64`\n▫️ پایتون: `3.11.10`\n▫️ پردازنده: `نامشخص`\n\n🔄 **وضعیت CPU:**\n▫️ استفاده: `51.8%`\n▫️ تعداد هسته: `8`\n▫️ فرکانس: `3050.0 MHz`\n▫️ روند: `🟢 پایدار`\n▫️ پیش‌بینی: `وضعیت پایدار برای هفته آینده`\n\n💾 **وضعیت RAM:**\n▫️ کل: `62.81 GB`\n▫️ استفاده شده: `52.57 GB (84.9%)`\n▫️ آزاد: `9.46 GB`\n▫️ روند: `🔴 افزایشی (هشدار)`\n▫️ پیش‌بینی: `احتمال پر شدن منابع در ساعات آینده`\n\n💿 **وضعیت SWAP:**\n▫️ کل: `0.00 B`\n▫️ استفاده شده: `0.00 B (0.0%)`\n▫️ آزاد: `0.00 B`\n\n💽 **وضعیت دیسک:**\n▫️ کل: `49.12 GB`\n▫️ استفاده شده: `23.84 GB (50.7%)`\n▫️ آزاد: `23.21 GB`\n▫️ روند: `🟢 پایدار`\n▫️ پیش‌بینی: `وضعیت پایدار برای هفته آینده`\n\n🌐 **وضعیت شبکه:**\n▫️ دریافت شده: `28.36 MB`\n▫️ ارسال شده: `1.73 MB`\n▫️ خطاهای دریافت: `0`\n▫️ خطاهای ارسال: `0`\n\n⏰ **اطلاعات زمانی:**\n▫️ زمان سرور: `2025-03-17 03:51:15`\n▫️ زمان راه‌اندازی: `2025-03-15 09:14:02`\n▫️ مدت کارکرد: `1 day, 18:37:13`\n\n📝 **وضعیت فرایندها:**\n▫️ تعداد کل: `14`\n", "timestamp": "2025-03-17T03:51:15.948078", "details": {"cpu_usage": 51.8, "ram_usage": 84.9, "disk_usage": 50.7, "predictions": {"cpu": "وضعیت پایدار برای هفته آینده", "ram": "احتمال پر شدن منابع در ساعات آینده", "disk": "وضعیت پایدار برای هفته آینده"}}}